<?xml version='1.0' encoding='UTF-8'?>
<sch:Button xmlns:sch="http://Baf.com/schemas" name="GetEnvStatus">
    <sch:seqIndex>16</sch:seqIndex>
    <sch:name>GetEnvStatus</sch:name>
    <sch:label>GetEnvStatus</sch:label>
    <sch:behavior>ExecuteMethod</sch:behavior>
    <sch:bmfTransactionName>GetEnvStatus</sch:bmfTransactionName>
    <sch:content></sch:content>
    <sch:appliesTo></sch:appliesTo>
    <sch:securityToken></sch:securityToken>
    <sch:description></sch:description>
    <sch:bmfTransaction isRef="true">GetEnvStatus</sch:bmfTransaction>
</sch:Button>